[
    {
        "model": "sales.categories",
        "pk": 1,
        "fields": {
            "name": "Electronics",
            "created": "2024-01-01T00:00:00Z"
        }
    },
    {
        "model": "sales.categories",
        "pk": 2,
        "fields": {
            "name": "Furniture",
            "created": "2024-01-02T00:00:00Z"
        }
    },
    {
        "model": "sales.customers",
        "pk": 1,
        "fields": {
            "name": "John Doe",
            "email": "johndoe@example.com",
            "created": "2024-01-01T00:00:00Z"
        }
    },
    {
        "model": "sales.products",
        "pk": 1,
        "fields": {
            "name": "Laptop",
            "price": 1000.00,
            "category": 1,
            "created": "2024-01-01T00:00:00Z"
        }
    },
    {
        "model": "sales.products",
        "pk": 2,
        "fields": {
            "name": "Sofa",
            "price": 500.00,
            "category": 2,
            "created": "2024-01-02T00:00:00Z"
        }
    },
    {
        "model": "sales.salesstatus",
        "pk": 1,
        "fields": {
            "status": "Pending",
            "created": "2024-01-01T00:00:00Z"
        }
    },
    {
        "model": "sales.sales",
        "pk": 1,
        "fields": {
            "customer": 1,
            "sale_status": 1,
            "total": 1000.00,
            "created_at": "2024-01-01T00:00:00Z",
            "updated_at": "2024-01-01T00:00:00Z",
            "user": null  
        }
    },
    {
        "model": "sales.salesdetails",
        "pk": 1,
        "fields": {
            "sale": 1,
            "product": 1,
            "quantity": 1,
            "price": 1000.00,
            "created": "2024-01-01T00:00:00Z"
        }
    },
    {
        "model": "sales.salesdetails",
        "pk": 2,
        "fields": {
            "sale": 1,
            "product": 2,
            "quantity": 1,
            "price": 500.00,
            "created": "2024-01-01T00:00:00Z"
        }
    }
]
